promptu/__init__.py
promptu/natural_list.py
promptu/plural.py
promptu/truncate.py
promptu-0.1.0.dist-info/LICENSE
promptu-0.1.0.dist-info/METADATA
promptu-0.1.0.dist-info/WHEEL
promptu-0.1.0.dist-info/RECORD
