Metadata-Version: 2.1
Name: promptu
Version: 0.1.0
Summary: Write dynamic LLM prompts as natural language
License: MIT
Keywords: prompt-engineering,llms,genai
Author: David
Author-email: 161997989+lintyourcode@users.noreply.github.com
Requires-Python: >=3.9,<4.0
Classifier: License :: OSI Approved :: MIT License
Classifier: Programming Language :: Python :: 3
Classifier: Programming Language :: Python :: 3.9
Classifier: Programming Language :: Python :: 3.10
Classifier: Programming Language :: Python :: 3.11
Classifier: Programming Language :: Python :: 3.12
